dyce/__init__.py
dyce/bt.py
dyce/h.py
dyce/lifecycle.py
dyce/p.py
dyce/r.py
dyce/symmetries.py
dyce/types.py
dyce/version.py
dyce/viz.py
dycelib-0.4.0.dist-info/LICENSE
dycelib-0.4.0.dist-info/METADATA
dycelib-0.4.0.dist-info/WHEEL
dycelib-0.4.0.dist-info/top_level.txt
dycelib-0.4.0.dist-info/RECORD
