Metadata-Version: 2.1
Name: dycelib
Version: 0.4.0
Summary: Simple Python tools for exploring dice outcomes and other finite discrete probabilities
Home-page: https://posita.github.io/dyce/0.4/
Author: Matt Bogosian
Author-email: matt@bogosian.net
License: MIT License
Platform: UNKNOWN
Classifier: Topic :: Education
Classifier: Topic :: Games/Entertainment
Classifier: Topic :: Scientific/Engineering :: Mathematics
Classifier: Topic :: Software Development :: Libraries :: Python Modules
Classifier: Development Status :: 4 - Beta
Classifier: Intended Audience :: Developers
Classifier: Intended Audience :: Education
Classifier: Intended Audience :: Science/Research
Classifier: License :: OSI Approved :: MIT License
Classifier: Operating System :: OS Independent
Classifier: Programming Language :: Python
Classifier: Programming Language :: Python :: 3.7
Classifier: Programming Language :: Python :: 3.8
Classifier: Programming Language :: Python :: 3.9
Classifier: Programming Language :: Python :: Implementation :: CPython
Classifier: Programming Language :: Python :: Implementation :: PyPy
License-File: LICENSE
Requires-Dist: typing-extensions ; python_version < "3.9"
Provides-Extra: dev
Requires-Dist: beartype ; extra == 'dev'
Requires-Dist: mike ; extra == 'dev'
Requires-Dist: mkdocs (!=1.2) ; extra == 'dev'
Requires-Dist: mkdocs-exclude ; extra == 'dev'
Requires-Dist: mkdocs-material ; extra == 'dev'
Requires-Dist: mkdocstrings ; extra == 'dev'
Requires-Dist: mypy ; extra == 'dev'
Requires-Dist: numpy ; extra == 'dev'
Requires-Dist: pre-commit ; extra == 'dev'
Requires-Dist: pytest-gitignore ; extra == 'dev'
Requires-Dist: sympy ; extra == 'dev'
Requires-Dist: tox ; extra == 'dev'
Requires-Dist: twine ; extra == 'dev'
